{
  "fetched_at": "2026-03-27T18:52:53Z",
  "source": "https://waterservices.usgs.gov/nwis/iv/",
  "gauges": {
    "Nisqually at McKenna": {
      "site_no": "12089500",
      "discharge_cfs": 3090.0,
      "discharge_dt": "2026-03-27T11:30:00.000-07:00",
      "stage_ft": 3.96,
      "stage_dt": "2026-03-27T11:30:00.000-07:00"
    },
    "Puyallup at Orting": {
      "site_no": "12093500",
      "discharge_cfs": 964.0,
      "discharge_dt": "2026-03-27T11:30:00.000-07:00",
      "stage_ft": 7.26,
      "stage_dt": "2026-03-27T11:30:00.000-07:00"
    },
    "Carbon at Orting": {
      "site_no": "12094000",
      "discharge_cfs": 607.0,
      "discharge_dt": "2026-03-27T11:00:00.000-07:00",
      "stage_ft": 7.3,
      "stage_dt": "2026-03-27T11:00:00.000-07:00"
    },
    "White at Buckley": {
      "site_no": "12099200",
      "discharge_cfs": 5030.0,
      "discharge_dt": "2026-03-27T11:30:00.000-07:00",
      "stage_ft": 43.8,
      "stage_dt": "2026-03-27T11:30:00.000-07:00"
    }
  }
}